korbyte_api_client/__init__.py
korbyte_api_client/api_client.py
korbyte_api_client/api_response.py
korbyte_api_client/configuration.py
korbyte_api_client/exceptions.py
korbyte_api_client/py.typed
korbyte_api_client/rest.py
korbyte_api_client/api/__init__.py
korbyte_api_client/api/daily_api.py
korbyte_api_client/api/details_api.py
korbyte_api_client/api/exchanges_api.py
korbyte_api_client/api/prepare_api.py
korbyte_api_client/api/tickers_api.py
korbyte_api_client/api/tracking_api.py
korbyte_api_client/models/__init__.py
korbyte_api_client/models/api_response_empty.py
korbyte_api_client/models/api_response_list_date_entry.py
korbyte_api_client/models/api_response_matrix.py
korbyte_api_client/models/api_response_object.py
korbyte_api_client/models/api_response_page_daily.py
korbyte_api_client/models/api_response_page_ticker.py
korbyte_api_client/models/api_response_tracking.py
korbyte_api_client/models/daily.py
korbyte_api_client/models/date_entry.py
korbyte_api_client/models/details.py
korbyte_api_client/models/exchange.py
korbyte_api_client/models/matrix.py
korbyte_api_client/models/page_daily.py
korbyte_api_client/models/page_ticker.py
korbyte_api_client/models/pageable_object.py
korbyte_api_client/models/prepare_params.py
korbyte_api_client/models/sort_object.py
korbyte_api_client/models/ticker.py
korbyte_api_client/models/tracking.py
korbyte_api_client-1.0.0.dist-info/METADATA
korbyte_api_client-1.0.0.dist-info/WHEEL
korbyte_api_client-1.0.0.dist-info/top_level.txt
korbyte_api_client-1.0.0.dist-info/RECORD
